{
    "batch_size": 32,
    "augment": "True",
    "n_aug": 4,
    "criterion_info": {
        "name": "Dice"
    },
    "dataset_info": {
        "test_data_path": "data/test",
        "train_data_path": "data/train",
        "val_data_path": "data/val"
    },
    "epochs": 30,
    "model_info": {
        "input_channels": 3,
        "model_path": "models/segnet.pth",
        "name": "SegNet"
    },
    "optimizer_info": {
        "lr": 0.0005,
        "name": "Adam",
        "weight_decay": 1e-08
    }
}